skylight_gui/__init__.py
skylight_gui/data/icon.png
skylight_gui-1.0b4.dist-info/LICENSE
skylight_gui-1.0b4.dist-info/METADATA
skylight_gui-1.0b4.dist-info/WHEEL
skylight_gui-1.0b4.dist-info/top_level.txt
skylight_gui-1.0b4.dist-info/RECORD
