Metadata-Version: 2.1
Name: skylight-gui
Version: 1.0b4
Summary: A package providing a GUI for the skylight_gui package.
Home-page: https://pypi.org/project/skylight-gui/
Author: Evripidis Gkanias
Author-email: ev.gkanias@ed.ac.uk
Maintainer: Evripidis Gkanias
Maintainer-email: ev.gkanias@ed.ac.uk
License: GPLv3+
Project-URL: Bug Tracker, https://github.com/evgkanias/sky-gui/issues
Project-URL: Source, https://github.com/evgkanias/sky-gui
Classifier: Development Status :: 4 - Beta
Classifier: Programming Language :: Python :: 3.9
Classifier: Intended Audience :: Science/Research
Classifier: Topic :: Scientific/Engineering :: Atmospheric Science
Classifier: License :: OSI Approved :: GNU General Public License v3 or later (GPLv3+)
Classifier: Operating System :: OS Independent
Classifier: Operating System :: Microsoft :: Windows :: Windows 11
Classifier: Topic :: Scientific/Engineering :: Visualization
Requires-Python: >=3.9
License-File: LICENSE
Requires-Dist: numpy (>=1.23.4)
Requires-Dist: scipy (>=1.9.3)
Requires-Dist: numba (>=0.56.3)
Requires-Dist: pytz (~=2021.1)
Requires-Dist: pyyaml (>=6.0)
Requires-Dist: requests (>=2.9.2)
Requires-Dist: pillow (>=9.2.0)
Requires-Dist: pandas (>=1.5.1)
Requires-Dist: matplotlib (>=3.6.2)
Requires-Dist: pysimplegui (>=4.60.4)
Requires-Dist: skylight
